PolicyParrot/__init__.py
PolicyParrot/buffers.py
PolicyParrot/policies.py
PolicyParrot/space_tests.py
policyparrot-0.0.2.dist-info/METADATA
policyparrot-0.0.2.dist-info/WHEEL
policyparrot-0.0.2.dist-info/licenses/LICENSE
policyparrot-0.0.2.dist-info/RECORD
