Metadata-Version: 2.1
Name: PolicyParrot
Version: 0.0.2
Summary: Abstract base classes for control policies
Project-URL: Homepage, https://github.com/WillDudley/PolicyParrot
Project-URL: Bug Tracker, https://github.com/WillDudley/PolicyParrot/issues
Author-email: WillDudley <will2346@live.co.uk>
License-File: LICENSE
Classifier: License :: OSI Approved :: MIT License
Classifier: Operating System :: OS Independent
Classifier: Programming Language :: Python :: 3
Requires-Python: >=3.7
Requires-Dist: gymnasium==0.26.2
